odpm/__init__.py
odpm/odpm.py
odpm/templates/default/__init__.py.template
odpm/templates/default/__manifest__.py.template
odpm/templates/default/controllers/__init__.py.template
odpm/templates/default/controllers/controllers.py.template
odpm/templates/default/demo/demo.xml.template
odpm/templates/default/models/__init__.py.template
odpm/templates/default/models/models.py.template
odpm/templates/default/security/ir.model.access.csv.template
odpm/templates/default/static/src/css/new_widget.css.template
odpm/templates/default/static/src/js/new_widget.js.template
odpm/templates/default/static/src/xml/new_widget.xml.template
odpm/templates/default/views/assets.xml.template
odpm/templates/default/views/templates.xml.template
odpm/templates/default/views/views.xml.template
odpm-0.0.18.dist-info/COPYING
odpm-0.0.18.dist-info/COPYING.lesser
odpm-0.0.18.dist-info/METADATA
odpm-0.0.18.dist-info/WHEEL
odpm-0.0.18.dist-info/entry_points.txt
odpm-0.0.18.dist-info/top_level.txt
odpm-0.0.18.dist-info/RECORD
