Metadata-Version: 2.1
Name: odpm
Version: 0.0.18
Summary: odoo development project mananagement
Home-page: https://github.com/aayartsev/odpm
Author: Yartsev Alexander
Author-email: a.yartsev@yartsev.by
License: LGPLv3
Keywords: odoo odpm
Platform: UNKNOWN
Classifier: Development Status :: 4 - Beta
Classifier: Intended Audience :: Developers
Classifier: License :: OSI Approved :: GNU Lesser General Public License v3 (LGPLv3)
Classifier: License :: OSI Approved :: GNU Lesser General Public License v3 or later (LGPLv3+)
Classifier: Programming Language :: Python
Classifier: Programming Language :: Python :: 3
Classifier: Topic :: Internet
Classifier: Topic :: Software Development :: Libraries
Classifier: Topic :: Software Development :: Libraries :: Python Modules
Requires-Python: >=3
